django_vue_start/__init__.py
django_vue_start/cli.py
django_vue_start/generator.py
django_vue_start/templates/.gitignore
django_vue_start/templates/.pre-commit-config.yaml
django_vue_start/templates/Makefile
django_vue_start/templates/README.md.j2
django_vue_start/templates/docker-compose.production.yml.j2
django_vue_start/templates/docker-compose.yml.j2
django_vue_start/templates/.github/workflows/ci.yml.j2
django_vue_start/templates/backend/.env.example
django_vue_start/templates/backend/Dockerfile
django_vue_start/templates/backend/conftest.py
django_vue_start/templates/backend/entrypoint.sh
django_vue_start/templates/backend/gunicorn.conf.py.j2
django_vue_start/templates/backend/manage.py.j2
django_vue_start/templates/backend/pytest.ini
django_vue_start/templates/backend/requirements.txt
django_vue_start/templates/backend/config/__init__.py
django_vue_start/templates/backend/config/urls.py.j2
django_vue_start/templates/backend/config/wsgi.py.j2
django_vue_start/templates/backend/config/settings/__init__.py
django_vue_start/templates/backend/config/settings/base.py.j2
django_vue_start/templates/backend/config/settings/local.py.j2
django_vue_start/templates/backend/config/settings/production.py.j2
django_vue_start/templates/backend/config/settings/test.py.j2
django_vue_start/templates/backend/core/__init__.py
django_vue_start/templates/backend/core/admin.py.j2
django_vue_start/templates/backend/core/apps.py.j2
django_vue_start/templates/backend/core/authentication.py
django_vue_start/templates/backend/core/models.py.j2
django_vue_start/templates/backend/core/serializers.py
django_vue_start/templates/backend/core/migrations/0001_initial.py
django_vue_start/templates/backend/core/migrations/__init__.py
django_vue_start/templates/backend/todos/__init__.py
django_vue_start/templates/backend/todos/admin.py.j2
django_vue_start/templates/backend/todos/apps.py.j2
django_vue_start/templates/backend/todos/models.py.j2
django_vue_start-1.1.6.dist-info/METADATA
django_vue_start-1.1.6.dist-info/WHEEL
django_vue_start-1.1.6.dist-info/entry_points.txt
django_vue_start-1.1.6.dist-info/licenses/LICENSE
django_vue_start-1.1.6.dist-info/RECORD
