Metadata-Version: 2.4
Name: django-vue-start
Version: 1.1.6
Summary: A production-ready Django + Vue.js project generator
Project-URL: Homepage, https://github.com/abdullafajal/django-vue-start
Project-URL: Documentation, https://github.com/abdullafajal/django-vue-start#readme
Project-URL: Repository, https://github.com/abdullafajal/django-vue-start
Project-URL: Issues, https://github.com/abdullafajal/django-vue-start/issues
Author-email: abdullafajal <abdullafajal@gmail.com>
License: MIT License
License-File: LICENSE
Keywords: cookiecutter,django,full-stack,generator,scaffold,starter,vue
Classifier: Development Status :: 4 - Beta
Classifier: Environment :: Console
Classifier: Framework :: Django :: 4.2
Classifier: Intended Audience :: Developers
Classifier: License :: OSI Approved :: MIT License
Classifier: Operating System :: OS Independent
Classifier: Programming Language :: Python :: 3
Classifier: Programming Language :: Python :: 3.8
Classifier: Programming Language :: Python :: 3.9
Classifier: Programming Language :: Python :: 3.10
Classifier: Programming Language :: Python :: 3.11
Classifier: Programming Language :: Python :: 3.12
Classifier: Topic :: Software Development :: Code Generators
Requires-Python: >=3.8
Requires-Dist: click>=8.1.0
Requires-Dist: jinja2>=3.1.0
Requires-Dist: rich>=13.0.0
Provides-Extra: dev
Requires-Dist: black>=23.0.0; extra == 'dev'
Requires-Dist: pytest-cov>=4.1.0; extra == 'dev'
Requires-Dist: pytest>=7.4.0; extra == 'dev'
Requires-Dist: ruff>=0.1.0; extra == 'dev'
